{
  "description": "GitopsService is the Schema for the gitopsservices API",
  "type": "object",
  "properties": {
    "apiVersion": {
      "description": "APIVersion defines the versioned schema of this representation of an object. Servers should convert recognized schemas to the latest internal value, and may reject unrecognized values. More info: https://git.k8s.io/community/contributors/devel/sig-architecture/api-conventions.md#resources",
      "type": [
        "string",
        "null"
      ],
      "enum": [
        "pipelines.openshift.io/v1alpha1"
      ]
    },
    "kind": {
      "description": "Kind is a string value representing the REST resource this object represents. Servers may infer this from the endpoint the client submits requests to. Cannot be updated. In CamelCase. More info: https://git.k8s.io/community/contributors/devel/sig-architecture/api-conventions.md#types-kinds",
      "type": [
        "string",
        "null"
      ],
      "enum": [
        "GitopsService"
      ]
    },
    "metadata": {
      "description": "Standard object's metadata. More info: https://git.k8s.io/community/contributors/devel/sig-architecture/api-conventions.md#metadata",
      "$ref": "_definitions.json#/definitions/io.k8s.apimachinery.pkg.apis.meta.v1.ObjectMeta"
    },
    "spec": {
      "description": "GitopsServiceSpec defines the desired state of GitopsService",
      "type": [
        "object",
        "null"
      ],
      "properties": {
        "consolePlugin": {
          "description": "ConsolePlugin defines the Resource configuration for the Console Plugin components",
          "type": [
            "object",
            "null"
          ],
          "properties": {
            "backend": {
              "description": "Backend defines the resource requests and limits for the backend service",
              "type": [
                "object",
                "null"
              ],
              "properties": {
                "resources": {
                  "description": "Resources defines the resource requests and limits for the backend service",
                  "type": [
                    "object",
                    "null"
                  ],
                  "properties": {
                    "claims": {
                      "description": "Claims lists the names of resources, defined in spec.resourceClaims,\nthat are used by this container.\n\nThis is an alpha field and requires enabling the\nDynamicResourceAllocation feature gate.\n\nThis field is immutable. It can only be set for containers.",
                      "type": [
                        "array",
                        "null"
                      ],
                      "items": {
                        "description": "ResourceClaim references one entry in PodSpec.ResourceClaims.",
                        "type": [
                          "object",
                          "null"
                        ],
                        "required": [
                          "name"
                        ],
                        "properties": {
                          "name": {
                            "description": "Name must match the name of one entry in pod.spec.resourceClaims of\nthe Pod where this field is used. It makes that resource available\ninside a container.",
                            "type": "string"
                          },
                          "request": {
                            "description": "Request is the name chosen for a request in the referenced claim.\nIf empty, everything from the claim is made available, otherwise\nonly the result of this request.",
                            "type": [
                              "string",
                              "null"
                            ]
                          }
                        },
                        "additionalProperties": false
                      },
                      "x-kubernetes-list-map-keys": [
                        "name"
                      ],
                      "x-kubernetes-list-type": "map"
                    },
                    "limits": {
                      "description": "Limits describes the maximum amount of compute resources allowed.\nMore info: https://kubernetes.io/docs/concepts/configuration/manage-resources-containers/",
                      "type": [
                        "object",
                        "null"
                      ],
                      "additionalProperties": {
                        "pattern": "^(\\+|-)?(([0-9]+(\\.[0-9]*)?)|(\\.[0-9]+))(([KMGTPE]i)|[numkMGTPE]|([eE](\\+|-)?(([0-9]+(\\.[0-9]*)?)|(\\.[0-9]+))))?$",
                        "x-kubernetes-int-or-string": true
                      }
                    },
                    "requests": {
                      "description": "Requests describes the minimum amount of compute resources required.\nIf Requests is omitted for a container, it defaults to Limits if that is explicitly specified,\notherwise to an implementation-defined value. Requests cannot exceed Limits.\nMore info: https://kubernetes.io/docs/concepts/configuration/manage-resources-containers/",
                      "type": [
                        "object",
                        "null"
                      ],
                      "additionalProperties": {
                        "pattern": "^(\\+|-)?(([0-9]+(\\.[0-9]*)?)|(\\.[0-9]+))(([KMGTPE]i)|[numkMGTPE]|([eE](\\+|-)?(([0-9]+(\\.[0-9]*)?)|(\\.[0-9]+))))?$",
                        "x-kubernetes-int-or-string": true
                      }
                    }
                  },
                  "additionalProperties": false
                }
              },
              "additionalProperties": false
            },
            "gitopsPlugin": {
              "description": "GitopsPlugin defines the resource requests and limits for the gitops plugin service",
              "type": [
                "object",
                "null"
              ],
              "properties": {
                "resources": {
                  "description": "Resources defines the resource requests and limits for the gitops plugin service",
                  "type": [
                    "object",
                    "null"
                  ],
                  "properties": {
                    "claims": {
                      "description": "Claims lists the names of resources, defined in spec.resourceClaims,\nthat are used by this container.\n\nThis is an alpha field and requires enabling the\nDynamicResourceAllocation feature gate.\n\nThis field is immutable. It can only be set for containers.",
                      "type": [
                        "array",
                        "null"
                      ],
                      "items": {
                        "description": "ResourceClaim references one entry in PodSpec.ResourceClaims.",
                        "type": [
                          "object",
                          "null"
                        ],
                        "required": [
                          "name"
                        ],
                        "properties": {
                          "name": {
                            "description": "Name must match the name of one entry in pod.spec.resourceClaims of\nthe Pod where this field is used. It makes that resource available\ninside a container.",
                            "type": "string"
                          },
                          "request": {
                            "description": "Request is the name chosen for a request in the referenced claim.\nIf empty, everything from the claim is made available, otherwise\nonly the result of this request.",
                            "type": [
                              "string",
                              "null"
                            ]
                          }
                        },
                        "additionalProperties": false
                      },
                      "x-kubernetes-list-map-keys": [
                        "name"
                      ],
                      "x-kubernetes-list-type": "map"
                    },
                    "limits": {
                      "description": "Limits describes the maximum amount of compute resources allowed.\nMore info: https://kubernetes.io/docs/concepts/configuration/manage-resources-containers/",
                      "type": [
                        "object",
                        "null"
                      ],
                      "additionalProperties": {
                        "pattern": "^(\\+|-)?(([0-9]+(\\.[0-9]*)?)|(\\.[0-9]+))(([KMGTPE]i)|[numkMGTPE]|([eE](\\+|-)?(([0-9]+(\\.[0-9]*)?)|(\\.[0-9]+))))?$",
                        "x-kubernetes-int-or-string": true
                      }
                    },
                    "requests": {
                      "description": "Requests describes the minimum amount of compute resources required.\nIf Requests is omitted for a container, it defaults to Limits if that is explicitly specified,\notherwise to an implementation-defined value. Requests cannot exceed Limits.\nMore info: https://kubernetes.io/docs/concepts/configuration/manage-resources-containers/",
                      "type": [
                        "object",
                        "null"
                      ],
                      "additionalProperties": {
                        "pattern": "^(\\+|-)?(([0-9]+(\\.[0-9]*)?)|(\\.[0-9]+))(([KMGTPE]i)|[numkMGTPE]|([eE](\\+|-)?(([0-9]+(\\.[0-9]*)?)|(\\.[0-9]+))))?$",
                        "x-kubernetes-int-or-string": true
                      }
                    }
                  },
                  "additionalProperties": false
                }
              },
              "additionalProperties": false
            }
          },
          "additionalProperties": false
        },
        "imagePullPolicy": {
          "description": "ImagePullPolicy defines the image pull policy for GitOps workloads",
          "type": [
            "string",
            "null"
          ],
          "enum": [
            "Always",
            "IfNotPresent",
            "Never"
          ]
        },
        "nodeSelector": {
          "description": "NodeSelector is a map of key value pairs used for node selection in the default workloads",
          "type": [
            "object",
            "null"
          ],
          "additionalProperties": {
            "type": [
              "string",
              "null"
            ]
          }
        },
        "runOnInfra": {
          "description": "InfraNodeEnabled will add infra NodeSelector to all the default workloads of gitops operator",
          "type": [
            "boolean",
            "null"
          ]
        },
        "tolerations": {
          "description": "Tolerations allow the default workloads to schedule onto nodes with matching taints",
          "type": [
            "array",
            "null"
          ],
          "items": {
            "description": "The pod this Toleration is attached to tolerates any taint that matches\nthe triple <key,value,effect> using the matching operator <operator>.",
            "type": [
              "object",
              "null"
            ],
            "properties": {
              "effect": {
                "description": "Effect indicates the taint effect to match. Empty means match all taint effects.\nWhen specified, allowed values are NoSchedule, PreferNoSchedule and NoExecute.",
                "type": [
                  "string",
                  "null"
                ]
              },
              "key": {
                "description": "Key is the taint key that the toleration applies to. Empty means match all taint keys.\nIf the key is empty, operator must be Exists; this combination means to match all values and all keys.",
                "type": [
                  "string",
                  "null"
                ]
              },
              "operator": {
                "description": "Operator represents a key's relationship to the value.\nValid operators are Exists and Equal. Defaults to Equal.\nExists is equivalent to wildcard for value, so that a pod can\ntolerate all taints of a particular category.",
                "type": [
                  "string",
                  "null"
                ]
              },
              "tolerationSeconds": {
                "description": "TolerationSeconds represents the period of time the toleration (which must be\nof effect NoExecute, otherwise this field is ignored) tolerates the taint. By default,\nit is not set, which means tolerate the taint forever (do not evict). Zero and\nnegative values will be treated as 0 (evict immediately) by the system.",
                "type": [
                  "integer",
                  "null"
                ],
                "format": "int64"
              },
              "value": {
                "description": "Value is the taint value the toleration matches to.\nIf the operator is Exists, the value should be empty, otherwise just a regular string.",
                "type": [
                  "string",
                  "null"
                ]
              }
            },
            "additionalProperties": false
          }
        }
      },
      "additionalProperties": false
    },
    "status": {
      "description": "GitopsServiceStatus defines the observed state of GitopsService",
      "type": [
        "object",
        "null"
      ]
    }
  },
  "x-kubernetes-group-version-kind": [
    {
      "group": "pipelines.openshift.io",
      "kind": "GitopsService",
      "version": "v1alpha1"
    }
  ],
  "additionalProperties": false,
  "$schema": "http://json-schema.org/schema#"
}